blockpipe_client/__init__.py
blockpipe_client-0.1.3.dist-info/LICENSE
blockpipe_client-0.1.3.dist-info/METADATA
blockpipe_client-0.1.3.dist-info/WHEEL
blockpipe_client-0.1.3.dist-info/top_level.txt
blockpipe_client-0.1.3.dist-info/RECORD
