Metadata-Version: 2.1
Name: blockpipe-client
Version: 0.1.3
Summary: A Python library for interacting with Blockpipe Endpoint API
Home-page: https://github.com/blockpipe/python
Author: blockpipe.io
Author-email: support@blockpipe.io
License: UNKNOWN
Platform: UNKNOWN
Classifier: Development Status :: 3 - Alpha
Classifier: Intended Audience :: Developers
Classifier: License :: OSI Approved :: Apache Software License
Classifier: Programming Language :: Python :: 3
Classifier: Programming Language :: Python :: 3.6
Classifier: Programming Language :: Python :: 3.7
Classifier: Programming Language :: Python :: 3.8
Requires-Python: >=3.6
License-File: LICENSE
Requires-Dist: requests
